MANIFEST.in
README.rst
setup.py
src/xinput/__init__.py
src/xinput/operate_xinput_device.py
src/xinput/tests.py
src/xinput.egg-info/PKG-INFO
src/xinput.egg-info/SOURCES.txt
src/xinput.egg-info/dependency_links.txt
src/xinput.egg-info/top_level.txt
src/xinput/bin/disable-mouse
src/xinput/bin/disable-touchpad
src/xinput/bin/enable-mouse
src/xinput/bin/enable-touchpad
src/xinput/bin/xinput-manage